Compressioner/__init__.py
Compressioner/PyTorch/__init__.py
Compressioner/PyTorch/automatic_mask_generator.py
Compressioner/PyTorch/build_sam.py
Compressioner/PyTorch/predictor.py
Compressioner/PyTorch/fastsam/__init__.py
Compressioner/PyTorch/fastsam/model.py
Compressioner/PyTorch/fastsam/predict.py
Compressioner/PyTorch/fastsam/prompt.py
Compressioner/PyTorch/fastsam/utils.py
Compressioner/PyTorch/fastsam/val.py
Compressioner/PyTorch/modeling/__init__.py
Compressioner/PyTorch/modeling/common.py
Compressioner/PyTorch/modeling/image_encoder.py
Compressioner/PyTorch/modeling/mask_decoder.py
Compressioner/PyTorch/modeling/prompt_encoder.py
Compressioner/PyTorch/modeling/sam.py
Compressioner/PyTorch/modeling/transformer.py
Compressioner/PyTorch/nas/__init__.py
Compressioner/PyTorch/nas/model.py
Compressioner/PyTorch/nas/predict.py
Compressioner/PyTorch/nas/val.py
Compressioner/PyTorch/rtdetr/__init__.py
Compressioner/PyTorch/rtdetr/model.py
Compressioner/PyTorch/rtdetr/predict.py
Compressioner/PyTorch/rtdetr/train.py
Compressioner/PyTorch/rtdetr/val.py
Compressioner/PyTorch/sam/__init__.py
Compressioner/PyTorch/sam/amg.py
Compressioner/PyTorch/sam/build.py
Compressioner/PyTorch/sam/model.py
Compressioner/PyTorch/sam/predict.py
Compressioner/PyTorch/sam/modules/__init__.py
Compressioner/PyTorch/sam/modules/decoders.py
Compressioner/PyTorch/sam/modules/encoders.py
Compressioner/PyTorch/sam/modules/sam.py
Compressioner/PyTorch/sam/modules/tiny_encoder.py
Compressioner/PyTorch/sam/modules/transformer.py
Compressioner/PyTorch/utils/__init__.py
Compressioner/PyTorch/utils/amg.py
Compressioner/PyTorch/utils/loss.py
Compressioner/PyTorch/utils/onnx.py
Compressioner/PyTorch/utils/ops.py
Compressioner/PyTorch/utils/transforms.py
Compressioner/PyTorch/yolo/__init__.py
Compressioner/PyTorch/yolo/model.py
Compressioner/PyTorch/yolo/classify/__init__.py
Compressioner/PyTorch/yolo/classify/predict.py
Compressioner/PyTorch/yolo/classify/train.py
ModelCompresionLight-0.1.8.dist-info/METADATA
ModelCompresionLight-0.1.8.dist-info/WHEEL
ModelCompresionLight-0.1.8.dist-info/top_level.txt
ModelCompresionLight-0.1.8.dist-info/RECORD
