Metadata-Version: 2.1
Name: ModelCompresionLight
Version: 0.1.8
Summary: Lighter Model Ensemble for model mc
Home-page: UNKNOWN
Author: CO-AI-TECH Team
Author-email: 710783785@qq.com
License: MIT
Platform: UNKNOWN
Requires-Python: >=3.6.2
Requires-Dist: thop
